README.rst
setup.py
data/__init__.py
data.egg-info/PKG-INFO
data.egg-info/SOURCES.txt
data.egg-info/dependency_links.txt
data.egg-info/requires.txt
data.egg-info/top_level.txt