Metadata-Version: 1.0
Name: data
Version: 0.1
Summary: Work with unicode/non-unicode data from files or strings uniformly.
Home-page: http://github.com/mbr/data
Author: Marc Brinkmann
Author-email: git@marcbrinkmann.de
License: MIT
Platform: UNKNOWN
